{"db_table": "SiteUser", "fields": {"id": {"sql_type": "SERIAL", "sql_onadd": "NOT NULL", "sql_ondrop": "", "sql_alter": [], "sql_engine": "postgresql", "column_name": "id"}, "name": {"sql_type": "varchar(255)", "sql_onadd": "", "sql_ondrop": "", "sql_alter": [], "sql_engine": "postgresql", "column_name": "name"}, "profession": {"sql_type": "varchar(255)", "sql_onadd": "", "sql_ondrop": "", "sql_alter": [], "sql_engine": "postgresql", "column_name": "profession"}, "age": {"sql_type": "integer", "sql_onadd": "", "sql_ondrop": "", "sql_alter": [], "sql_engine": "postgresql", "column_name": "age"}}}